pybuilder_archetype_base/__init__.py
pybuilder_archetype_base/errors.py
pybuilder_archetype_base/helpers.py
pybuilder_archetype_base/messages.py
pybuilder_archetype_base/resources/README.md
pybuilder_archetype_base/resources/__init__.py
pybuilder_archetype_base/resources/gitignore
pybuilder_archetype_base/resources/requirements.txt
pybuilder_archetype_base/resources/setup.py
pybuilder_archetype_base/resources/config/constants.py
pybuilder_archetype_base/resources/config/messages.py
pybuilder_archetype_base/resources/config/logger/logger.yml
pybuilder_archetype_base/resources/tests/__init__.py
pybuilder_archetype_base/resources/tests/test_example.py
pybuilder_archetype_base/resources/utils/helpers.py
pybuilder_archetype_base/resources/utils/logging/__init__.py
pybuilder_archetype_base/resources/utils/logging/handlers.py
pybuilder_archetype_base-0.1.1.dist-info/METADATA
pybuilder_archetype_base-0.1.1.dist-info/WHEEL
pybuilder_archetype_base-0.1.1.dist-info/namespace_packages.txt
pybuilder_archetype_base-0.1.1.dist-info/top_level.txt
pybuilder_archetype_base-0.1.1.dist-info/zip-safe
pybuilder_archetype_base-0.1.1.dist-info/RECORD
